mymodules/__init__.py
mymodules/messages.py
mymodules/preprocessing.py
mymodules/sessions.py
nlpprocess-0.1.dist-info/METADATA
nlpprocess-0.1.dist-info/WHEEL
nlpprocess-0.1.dist-info/top_level.txt
nlpprocess-0.1.dist-info/RECORD
