Metadata-Version: 2.1
Name: nlpprocess
Version: 0.1
Summary: UNKNOWN
Home-page: UNKNOWN
Author: Sina Heydari
Author-email: sinaa.heydari.76@gmail.com
License: UNKNOWN
Platform: UNKNOWN
Classifier: Programming Language :: Python :: 3
Requires-Python: ~=3.10
Requires-Dist: dill
Requires-Dist: matplotlib
Requires-Dist: numpy
Requires-Dist: pandas
Requires-Dist: spacy
Requires-Dist: spacy-cleaner
Requires-Dist: think
Requires-Dist: tqdm
